dpshell/__init__.py
dpshell/empty_check.py
dpshell-1.0.0.dist-info/LICENSE
dpshell-1.0.0.dist-info/METADATA
dpshell-1.0.0.dist-info/WHEEL
dpshell-1.0.0.dist-info/entry_points.txt
dpshell-1.0.0.dist-info/top_level.txt
dpshell-1.0.0.dist-info/RECORD
