Metadata-Version: 2.1
Name: dpshell
Version: 1.0.0
Summary: A Python command line tool to deal with file information extraction. 
Home-page: https://github.com/Listen180/pyshell
Author: Sen LEI
Author-email: sen.lei@outlook.com
License: BSD 3-clause
Keywords: python,package,pypi,shell,file info extraction
Platform: UNKNOWN
Classifier: Development Status :: 3 - Alpha
Classifier: Programming Language :: Python :: 3.6
Classifier: License :: OSI Approved :: BSD License
Classifier: Operating System :: OS Independent
Requires-Dist: auto-pypi
